loka_light/__init__.py
loka_light/applications/__init__.py
loka_light/applications/scenarios.py
loka_light/cognition/__init__.py
loka_light/cognition/base.py
loka_light/cognition/models.py
loka_light/core/__init__.py
loka_light/core/algebras.py
loka_light/core/loka.py
loka_light/core/polarity.py
loka_light/core/value.py
loka_light/devices/__init__.py
loka_light/devices/base.py
loka_light/devices/coding.py
loka_light/devices/communication.py
loka_light/devices/components.py
loka_light/devices/detectors.py
loka_light/devices/media.py
loka_light/devices/passport.py
loka_light/devices/pseudomultipolar.py
loka_light/devices/sigma_guard.py
loka_light/devices/sources.py
loka_light/physics/__init__.py
loka_light/physics/composition.py
loka_light/physics/multipolar_cascade.py
loka_light/physics/multipolar_fields.py
loka_light/physics/multipolar_quantum.py
loka_light/physics/multipolar_relativity.py
loka_light/physics/multipolar_wave.py
loka_light/physics/sigma.py
loka_light/simulation/__init__.py
loka_light/simulation/engine.py
loka_light-1.1.0.dist-info/licenses/LICENSE
loka_light-1.1.0.dist-info/METADATA
loka_light-1.1.0.dist-info/WHEEL
loka_light-1.1.0.dist-info/top_level.txt
loka_light-1.1.0.dist-info/RECORD
