Metadata-Version: 2.4
Name: loka_light
Version: 1.1.0
Summary: Compact multipolar toolkit
Author-email: Maxim Radaev <radaevm@gmail.com>
License: CC BY-NC 4.0
Requires-Python: >=3.11
License-File: LICENSE
Requires-Dist: numpy>=1.24
Provides-Extra: dev
Requires-Dist: pytest>=8; extra == "dev"
Requires-Dist: mypy>=1.10; extra == "dev"
Requires-Dist: ruff>=0.5; extra == "dev"
Dynamic: license-file
